<PAMDataset>
  <PAMRasterBand band="1">
    <Metadata>
      <MDI key="STATISTICS_MAXIMUM">255</MDI>
      <MDI key="STATISTICS_MEAN">93.518677961863</MDI>
      <MDI key="STATISTICS_MINIMUM">15</MDI>
      <MDI key="STATISTICS_STDDEV">57.271550143435</MDI>
      <MDI key="STATISTICS_VALID_PERCENT">99.71</MDI>
    </Metadata>
  </PAMRasterBand>
  <PAMRasterBand band="2">
    <Metadata>
      <MDI key="STATISTICS_MAXIMUM">255</MDI>
      <MDI key="STATISTICS_MEAN">113.4157911988</MDI>
      <MDI key="STATISTICS_MINIMUM">35</MDI>
      <MDI key="STATISTICS_STDDEV">41.263736679616</MDI>
      <MDI key="STATISTICS_VALID_PERCENT">99.71</MDI>
    </Metadata>
  </PAMRasterBand>
  <PAMRasterBand band="3">
    <Metadata>
      <MDI key="STATISTICS_MAXIMUM">255</MDI>
      <MDI key="STATISTICS_MEAN">93.410975984753</MDI>
      <MDI key="STATISTICS_MINIMUM">0</MDI>
      <MDI key="STATISTICS_STDDEV">35.303941384229</MDI>
      <MDI key="STATISTICS_VALID_PERCENT">99.71</MDI>
    </Metadata>
  </PAMRasterBand>
</PAMDataset>
